{
	"info": {
		"_postman_id": "1ea2678e-5ca0-44cd-998e-6c7c97af040e",
		"name": "feature",
		"schema": "https://schema.getpostman.com/json/collection/v2.1.0/collection.json"
	},
	"item": [
		{
			"name": "Создание пустого комментария",
			"event": [
				{
					"listen": "test",
					"script": {
						"exec": [
							"pm.test(\"Код 400 \",()=>{\r",
							"pm.response.to.have.status(400);\r",
							"pm.response.to.be.withBody;\r",
							"pm.response.to.be.json;\r",
							"});"
						],
						"type": "text/javascript"
					}
				}
			],
			"request": {
				"method": "POST",
				"header": [],
				"body": {
					"mode": "raw",
					"raw": "{\r\n    \"text\": \"\"\r\n}",
					"options": {
						"raw": {
							"language": "json"
						}
					}
				},
				"url": {
					"raw": "http://localhost:8080/users/:userId/comments/events/:eventId",
					"protocol": "http",
					"host": [
						"localhost"
					],
					"port": "8080",
					"path": [
						"users",
						":userId",
						"comments",
						"events",
						":eventId"
					],
					"variable": [
						{
							"key": "userId",
							"value": "1"
						},
						{
							"key": "eventId",
							"value": "1"
						}
					]
				}
			},
			"response": []
		},
		{
			"name": "Создание комментария для не опубликованного события",
			"event": [
				{
					"listen": "test",
					"script": {
						"exec": [
							"pm.test(\"Код 409\",()=>{\r",
							"pm.response.to.have.status(409);\r",
							"pm.response.to.be.withBody;\r",
							"pm.response.to.be.json;\r",
							"});"
						],
						"type": "text/javascript"
					}
				}
			],
			"request": {
				"method": "POST",
				"header": [],
				"body": {
					"mode": "raw",
					"raw": "{\r\n    \"text\": \"test comment\"\r\n}",
					"options": {
						"raw": {
							"language": "json"
						}
					}
				},
				"url": {
					"raw": "http://localhost:8080/users/:userId/comments/events/:eventId",
					"protocol": "http",
					"host": [
						"localhost"
					],
					"port": "8080",
					"path": [
						"users",
						":userId",
						"comments",
						"events",
						":eventId"
					],
					"variable": [
						{
							"key": "userId",
							"value": "1"
						},
						{
							"key": "eventId",
							"value": "5"
						}
					]
				}
			},
			"response": []
		},
		{
			"name": "Создание комментария",
			"event": [
				{
					"listen": "test",
					"script": {
						"exec": [
							"pm.test(\"Статус 201\",()=>{\r",
							"    pm.response.to.have.status(201);\r",
							"})\r",
							"const target = pm.response.json();\r",
							"pm.test(\"Проверка текста комментария\",()=>{\r",
							"pm.expect(target.text).to.eqls(\"test comment\");\r",
							"});"
						],
						"type": "text/javascript"
					}
				}
			],
			"request": {
				"method": "POST",
				"header": [],
				"body": {
					"mode": "raw",
					"raw": "{\r\n    \"text\": \"test comment\"\r\n}",
					"options": {
						"raw": {
							"language": "json"
						}
					}
				},
				"url": {
					"raw": "http://localhost:8080/users/:userId/comments/events/:eventId",
					"protocol": "http",
					"host": [
						"localhost"
					],
					"port": "8080",
					"path": [
						"users",
						":userId",
						"comments",
						"events",
						":eventId"
					],
					"variable": [
						{
							"key": "userId",
							"value": "1"
						},
						{
							"key": "eventId",
							"value": "2"
						}
					]
				}
			},
			"response": []
		},
		{
			"name": "Изменение комментария",
			"event": [
				{
					"listen": "test",
					"script": {
						"exec": [
							"pm.test(\"Статус 200\", ()=>{\r",
							"pm.response.to.have.status(200);\r",
							"});\r",
							"const target = pm.response.json();\r",
							"pm.test(\"Проверка изменения комментраия\",()=>{\r",
							"pm.expect(target.text).to.eqls(\"update comment\");\r",
							"});"
						],
						"type": "text/javascript"
					}
				}
			],
			"request": {
				"method": "PATCH",
				"header": [],
				"body": {
					"mode": "raw",
					"raw": "{\r\n    \"text\": \"update comment\"\r\n}",
					"options": {
						"raw": {
							"language": "json"
						}
					}
				},
				"url": {
					"raw": "http://localhost:8080/users/:userId/comments/:commentId/events/:eventId",
					"protocol": "http",
					"host": [
						"localhost"
					],
					"port": "8080",
					"path": [
						"users",
						":userId",
						"comments",
						":commentId",
						"events",
						":eventId"
					],
					"variable": [
						{
							"key": "userId",
							"value": "1"
						},
						{
							"key": "commentId",
							"value": "1"
						},
						{
							"key": "eventId",
							"value": "2"
						}
					]
				}
			},
			"response": []
		},
		{
			"name": "Получение коментариев пользователя для события",
			"event": [
				{
					"listen": "test",
					"script": {
						"exec": [
							"pm.test(\"Статус 200\",()=>{\r",
							"pm.response.to.have.status(200);\r",
							"});\r",
							"const target = pm.response.json();\r",
							"pm.test(\"Проверка евента с комментарием\",()=>{\r",
							"    pm.expect(target).to.be.not.null;\r",
							"    pm.expect(target[0].event.id).to.eql(2);\r",
							"});"
						],
						"type": "text/javascript"
					}
				}
			],
			"request": {
				"method": "GET",
				"header": [],
				"url": {
					"raw": "http://localhost:8080/users/:userId/comments/events/:eventId",
					"protocol": "http",
					"host": [
						"localhost"
					],
					"port": "8080",
					"path": [
						"users",
						":userId",
						"comments",
						"events",
						":eventId"
					],
					"variable": [
						{
							"key": "userId",
							"value": "1"
						},
						{
							"key": "eventId",
							"value": "2"
						}
					]
				}
			},
			"response": []
		},
		{
			"name": "Создание комментария другому событию",
			"event": [
				{
					"listen": "test",
					"script": {
						"exec": [
							"pm.test(\"Статус 201\",()=>{\r",
							"    pm.response.to.have.status(201);\r",
							"})\r",
							"const target = pm.response.json();\r",
							"pm.test(\"Проверка текста комментария\",()=>{\r",
							"pm.expect(target.text).to.eqls(\"test comment\");\r",
							"});"
						],
						"type": "text/javascript"
					}
				}
			],
			"request": {
				"method": "POST",
				"header": [],
				"body": {
					"mode": "raw",
					"raw": "{\r\n    \"text\": \"test comment\"\r\n}",
					"options": {
						"raw": {
							"language": "json"
						}
					}
				},
				"url": {
					"raw": "http://localhost:8080/users/:userId/comments/events/:eventId",
					"protocol": "http",
					"host": [
						"localhost"
					],
					"port": "8080",
					"path": [
						"users",
						":userId",
						"comments",
						"events",
						":eventId"
					],
					"variable": [
						{
							"key": "userId",
							"value": "1"
						},
						{
							"key": "eventId",
							"value": "3"
						}
					]
				}
			},
			"response": []
		},
		{
			"name": "Получение пользователем всех своих комментариев",
			"event": [
				{
					"listen": "test",
					"script": {
						"exec": [
							"pm.test(\"Статус 200\",()=>{\r",
							"pm.response.to.have.status(200);\r",
							"});\r",
							"const target = pm.response.json();\r",
							"pm.test(\"Проверка евента с комментарием\",()=>{\r",
							"    pm.expect(target).to.be.not.null;\r",
							"    pm.expect(target[0].event.id).to.eql(2);\r",
							"    pm.expect(target[1].event.id).to.eql(3);\r",
							"});"
						],
						"type": "text/javascript"
					}
				}
			],
			"request": {
				"method": "GET",
				"header": [],
				"url": {
					"raw": "http://localhost:8080/users/:userId/comments",
					"protocol": "http",
					"host": [
						"localhost"
					],
					"port": "8080",
					"path": [
						"users",
						":userId",
						"comments"
					],
					"variable": [
						{
							"key": "userId",
							"value": "1"
						}
					]
				}
			},
			"response": []
		},
		{
			"name": "Удаления лайка",
			"event": [
				{
					"listen": "test",
					"script": {
						"exec": [
							"pm.test(\"Статус 204\",()=>{\r",
							"pm.response.to.have.status(204);\r",
							"});"
						],
						"type": "text/javascript"
					}
				}
			],
			"request": {
				"method": "DELETE",
				"header": [],
				"url": {
					"raw": "http://localhost:8080/users/:userId/comments/:commentId/events/:eventId",
					"protocol": "http",
					"host": [
						"localhost"
					],
					"port": "8080",
					"path": [
						"users",
						":userId",
						"comments",
						":commentId",
						"events",
						":eventId"
					],
					"variable": [
						{
							"key": "userId",
							"value": "1"
						},
						{
							"key": "commentId",
							"value": "1"
						},
						{
							"key": "eventId",
							"value": "2"
						}
					]
				}
			},
			"response": []
		},
		{
			"name": "Удаление коммента с не правильными данными",
			"event": [
				{
					"listen": "test",
					"script": {
						"exec": [
							"pm.test(\"Статус 404\",()=>{\r",
							"    pm.response.to.have.status(404);\r",
							"});"
						],
						"type": "text/javascript"
					}
				}
			],
			"request": {
				"method": "DELETE",
				"header": [],
				"url": {
					"raw": "http://localhost:8080/users/:userId/comments/:commentId/events/:eventId",
					"protocol": "http",
					"host": [
						"localhost"
					],
					"port": "8080",
					"path": [
						"users",
						":userId",
						"comments",
						":commentId",
						"events",
						":eventId"
					],
					"variable": [
						{
							"key": "userId",
							"value": "3"
						},
						{
							"key": "commentId",
							"value": "3"
						},
						{
							"key": "eventId",
							"value": "3"
						}
					]
				}
			},
			"response": []
		}
	]
}